cmakepresets/__init__.py
cmakepresets/cli.py
cmakepresets/constants.py
cmakepresets/exceptions.py
cmakepresets/log.py
cmakepresets/macros.py
cmakepresets/parser.py
cmakepresets/paths.py
cmakepresets/presets.py
cmakepresets/schema.py
cmakepresets/utils.py
cmakepresets-0.4.1.dist-info/METADATA
cmakepresets-0.4.1.dist-info/WHEEL
cmakepresets-0.4.1.dist-info/entry_points.txt
cmakepresets-0.4.1.dist-info/RECORD
