Metadata-Version: 2.4
Name: cmakepresets
Version: 0.4.1
Summary: A library for parsing CMakePresets.json
Project-URL: Homepage, https://github.com/tkk2112/cmakepresets
Project-URL: Issues, https://github.com/tkk2112/cmakepresets/issues
Project-URL: Repository, https://github.com/tkk2112/cmakepresets.git
Author-email: Thomas Kristensen <thomas@sl.m04r.space>
License-Expression: MIT
Keywords: CMakePresets.json,cmake,presets
Classifier: Development Status :: 4 - Beta
Classifier: Operating System :: OS Independent
Classifier: Programming Language :: Python :: 3.11
Requires-Python: >=3.11
Requires-Dist: jsonschema>=4.23.0
Requires-Dist: requests>=2.32.3
Requires-Dist: rich>=13.9.4
